maxllg/__init__.py
maxllg/params.py
maxllg/solver/__init__.py
maxllg/solver/solver.py
maxllg-0.0.1.dist-info/LICENSE
maxllg-0.0.1.dist-info/METADATA
maxllg-0.0.1.dist-info/WHEEL
maxllg-0.0.1.dist-info/top_level.txt
maxllg-0.0.1.dist-info/RECORD
