Metadata-Version: 2.1
Name: maxllg
Version: 0.0.1
Summary: A package for interacting with the MaxLLG solver and its outputs. 
Home-page: https://maxllg.com/
Author: Samuel Morrell
Author-email: s.a.f.morrell@exeter.ac.uk
License: UNKNOWN
Platform: UNKNOWN
Classifier: Programming Language :: Python :: 3
Classifier: License :: OSI Approved :: MIT License
Classifier: Operating System :: OS Independent
Requires-Python: >=3.6
License-File: LICENSE
